despoilerizer/__init__.py
despoilerizer/__main__.py
despoilerizer/__version__.py
despoilerizer/core.py
despoilerizer-1.0.1.dist-info/LICENSE
despoilerizer-1.0.1.dist-info/WHEEL
despoilerizer-1.0.1.dist-info/METADATA
despoilerizer-1.0.1.dist-info/RECORD
