Metadata-Version: 2.1
Name: despoilerizer
Version: 1.0.1
Summary: Remove spoilers from files.
Home-page: https://github.com/dpdani/despoilerizer
License: GPL-3.0-only
Author: Daniele Parmeggiani
Author-email: git@danieleparmeggiani.me
Requires-Python: >=3.6
Classifier: Environment :: Console
Classifier: Intended Audience :: Developers
Classifier: Intended Audience :: End Users/Desktop
Classifier: License :: OSI Approved :: GNU General Public License v3 (GPLv3)
Classifier: Natural Language :: English
Classifier: Operating System :: OS Independent
Classifier: Programming Language :: Python :: 3
Classifier: Programming Language :: Python :: 3.6
Classifier: Programming Language :: Python :: 3.7
Classifier: Programming Language :: Python :: 3.8
Classifier: Programming Language :: Python :: 3.9
Classifier: Topic :: Text Processing
Classifier: Topic :: Text Processing :: Filters
Classifier: Topic :: Utilities
Requires-Dist: click
Project-URL: Repository, https://github.com/dpdani/despoilerizer
